manim_gearbox/__init__.py
manim_gearbox/gear_mobject/__init__.py
manim_gearbox/gear_mobject/Gear_mobject.py
manim_gearbox-0.2.4.dist-info/entry_points.txt
manim_gearbox-0.2.4.dist-info/LICENSE.txt
manim_gearbox-0.2.4.dist-info/WHEEL
manim_gearbox-0.2.4.dist-info/METADATA
manim_gearbox-0.2.4.dist-info/RECORD
