Metadata-Version: 2.1
Name: manim-gearbox
Version: 0.2.4
Summary: This is an extension of Manim that helps drawing nice looking gears.
Home-page: https://github.com/GarryBGoode/manim-GearBox
Author: GarryBGoode
Author-email: bgeri91@gmail.com
Requires-Python: >=3.7,<3.11
Classifier: Programming Language :: Python :: 3
Classifier: Programming Language :: Python :: 3.10
Classifier: Programming Language :: Python :: 3.7
Classifier: Programming Language :: Python :: 3.8
Classifier: Programming Language :: Python :: 3.9
Requires-Dist: manim (>=0.13.1)
Requires-Dist: scipy
Project-URL: Repository, https://github.com/GarryBGoode/manim-GearBox
